cms_forms/__init__.py
cms_forms/admin.py
cms_forms/cms_plugins.py
cms_forms/config.py
cms_forms/config_defaults.py
cms_forms/enums.py
cms_forms/fields.py
cms_forms/forms.py
cms_forms/importer.py
cms_forms/json.py
cms_forms/models.py
cms_forms/urls.py
cms_forms/views.py
cms_forms/migrations/0001_initial.py
cms_forms/migrations/__init__.py
cms_forms/plugin_forms/__init__.py
cms_forms/plugin_forms/buttons.py
cms_forms/plugin_forms/choices.py
cms_forms/plugin_forms/fields.py
cms_forms/plugin_forms/forms.py
cms_forms/plugin_forms/widgets.py
cms_forms/plugins/__init__.py
cms_forms/plugins/buttons.py
cms_forms/plugins/choices.py
cms_forms/plugins/fields.py
cms_forms/plugins/forms.py
cms_forms/plugins/widgets.py
cms_forms/static/cms_forms/forms.js
cms_forms/templates/cms_forms/field.html
cms_forms/templates/cms_forms/formbutton.html
cms_forms/templates/cms_forms/formfieldplugin.html
cms_forms/templates/cms_forms/formplugin.html
django_cms_forms-0.1.2.dist-info/LICENSE
django_cms_forms-0.1.2.dist-info/METADATA
django_cms_forms-0.1.2.dist-info/WHEEL
django_cms_forms-0.1.2.dist-info/top_level.txt
django_cms_forms-0.1.2.dist-info/RECORD
