Metadata-Version: 2.1
Name: django-cms-forms
Version: 0.1.2
Summary: Set of Django CMS plugins for creating forms
Home-page: https://github.com/sim1234/cms_forms
Author: Szymon Zmilczak
Author-email: szymon.zmilczak@gmail.com
Maintainer: Szymon Zmilczak
Maintainer-email: szymon.zmilczak@gmail.com
License: MIT
Keywords: django,django cms,cms,forms
Platform: UNKNOWN
Classifier: Development Status :: 3 - Alpha
Classifier: Intended Audience :: Developers
Classifier: Programming Language :: Python :: 3
Classifier: Programming Language :: Python :: 3.6
Classifier: Programming Language :: Python :: 3.7
Classifier: Programming Language :: Python :: 3.8
Classifier: Framework :: Django
Classifier: Framework :: Django :: 2.2
Classifier: Natural Language :: English
Classifier: License :: OSI Approved :: MIT License
Classifier: Operating System :: OS Independent
Requires-Python: >=3.6
Requires-Dist: django-cms (>=3.7)
